{
  "intro": {
    "visible": true,
    "title": "Put your brand *where the builders are.*",
    "body": "Ummah Tech is a South African non-profit initiative that brings together Muslim founders, technologists, entrepreneurs, researchers and creatives committed to building technology with faith, purpose and long-term responsibility at its centre.\n\nPartnership places your organisation inside that network. "
  },
  "why": {
    "visible": true,
    "heading": "Why partner with Ummah Tech",
    "items": [
      {
        "icon": "network",
        "title": "Reach a network of tech leaders",
        "body": "Visibility among Muslim technologists, entrepreneurs, developers and innovators shaping the future of technology."
      },
      {
        "icon": "scale",
        "title": "Align with Islamic values",
        "body": "Align your intention to please Allah (swt) with a commitment to ethical innovation and socially responsible technology. "
      },
      {
        "icon": "lightbulb",
        "title": "Showcase your brand",
        "body": "A direct line to an engaged audience of professionals, entrepreneurs and decision-makers across the tech industry."
      },
      {
        "icon": "sprout",
        "title": "Grow the community",
        "body": "Help build a space where Muslim professionals can collaborate and innovate solutions that serve the Ummah and society. "
      }
    ]
  },
  "partners": {
    "visible": true,
    "heading": "Our 2026 partners",
    "description": "The organisations partnering with Ummah Tech 2026, at every tier."
  },
  "tiers": {
    "visible": true,
    "heading": "Partnership tiers",
    "lead": "Three tiers, scaled by prominence. Each includes everything in the tier below it, and complimentary tickets come with all three.",
    "groups": [
      {
        "heading": "Allocation",
        "rows": [
          {
            "label": "Slots available",
            "platinum": "1",
            "gold": "3",
            "silver": "6"
          },
          {
            "label": "Free tickets",
            "platinum": "8",
            "gold": "4",
            "silver": "2"
          }
        ]
      },
      {
        "heading": "Benefits",
        "rows": [
          {
            "label": "Speaker slot or panel discussion",
            "platinum": "yes"
          },
          {
            "label": "Lanyard branding",
            "platinum": "yes"
          },
          {
            "label": "Placement at the venue",
            "platinum": "Premium",
            "gold": "yes"
          },
          {
            "label": "Propose a topic and speaker",
            "platinum": "yes",
            "gold": "yes"
          },
          {
            "label": "Branding on the ticketing website",
            "platinum": "yes",
            "gold": "yes"
          },
          {
            "label": "Branding on social media posts",
            "platinum": "yes",
            "gold": "yes"
          },
          {
            "label": "Branding on the event website",
            "platinum": "yes",
            "gold": "yes",
            "silver": "yes"
          },
          {
            "label": "Partnership announcement — social media & WhatsApp",
            "platinum": "yes",
            "gold": "yes",
            "silver": "yes"
          },
          {
            "label": "Exhibition table",
            "platinum": "yes",
            "gold": "yes",
            "silver": "yes"
          }
        ]
      }
    ]
  },
  "contact": {
    "visible": true,
    "heading": "Start the conversation.",
    "description": "Tell us who you are and what you have in mind, and we'll come back with the prospectus and a proposal shaped around it.",
    "successMessage": "Thanks — we've got your message and we'll come back to you with the prospectus."
  }
}